dataneuron/__init__.py
dataneuron/api/claude_api.py
dataneuron/api/main.py
dataneuron/api/ollama_api.py
dataneuron/api/openai_api.py
dataneuron/cli.py
dataneuron/cmd/ask_cmd.py
dataneuron/cmd/chat_cmd.py
dataneuron/cmd/context_init_cmd.py
dataneuron/cmd/db_init_cmd.py
dataneuron/cmd/mark_clients_cmd.py
dataneuron/cmd/report_cmd.py
dataneuron/core/context_loader.py
dataneuron/core/dashboard_manager.py
dataneuron/core/data_neuron.py
dataneuron/core/nlp_helpers/cte_handler.py
dataneuron/core/nlp_helpers/is_cte.py
dataneuron/core/query_refiner.py
dataneuron/core/sql_query_filter.py
dataneuron/core/sql_query_filters/client_filter.py
dataneuron/core/sql_query_filters/main.py
dataneuron/core/sql_query_filters/sql_components.py
dataneuron/core/sql_query_filters/sql_parser.py
dataneuron/core/sql_query_filters/sub_query_handler.py
dataneuron/core/sql_query_filters/where_clause_handler.py
dataneuron/core/sql_validator.py
dataneuron/db_operations/base.py
dataneuron/db_operations/clickhouse.py
dataneuron/db_operations/database_helpers.py
dataneuron/db_operations/duckdb.py
dataneuron/db_operations/error_handler.py
dataneuron/db_operations/exceptions.py
dataneuron/db_operations/factory.py
dataneuron/db_operations/mssql.py
dataneuron/db_operations/mysql.py
dataneuron/db_operations/postgres.py
dataneuron/db_operations/sqlite.py
dataneuron/lambda_handler.py
dataneuron/prompts/query_refinement_prompt.py
dataneuron/prompts/report_generation_prompt.py
dataneuron/prompts/sql_query_prompt.py
dataneuron/prompts/yaml_generation_prompt.py
dataneuron/server.py
dataneuron/utils/date_functions.py
dataneuron/utils/file_utils.py
dataneuron/utils/print.py
dataneuron/utils/serialization.py
dataneuron/utils/stream_print.py
dataneuron-0.3.2.dist-info/LICENSE
dataneuron-0.3.2.dist-info/METADATA
dataneuron-0.3.2.dist-info/WHEEL
dataneuron-0.3.2.dist-info/entry_points.txt
dataneuron-0.3.2.dist-info/RECORD
