Metadata-Version: 2.1
Name: dataneuron
Version: 0.3.2
Summary: An AI Data framework to create AI Data Analyst
License: MIT
Author: Vysakh Sreenivasan
Author-email: srvysakh@gmail.com
Requires-Python: >=3.8,<4.0
Classifier: License :: OSI Approved :: MIT License
Classifier: Programming Language :: Python :: 3
Classifier: Programming Language :: Python :: 3.8
Classifier: Programming Language :: Python :: 3.9
Classifier: Programming Language :: Python :: 3.10
Classifier: Programming Language :: Python :: 3.11
Classifier: Programming Language :: Python :: 3.12
Provides-Extra: all
Provides-Extra: clickhouse
Provides-Extra: csv
Provides-Extra: mssql
Provides-Extra: mysql
Provides-Extra: pdf
Provides-Extra: postgres
Provides-Extra: sqlite
Requires-Dist: click (>=8.1.3,<9.0.0)
Requires-Dist: clickhouse-connect (>=0.7.17,<0.8.0) ; extra == "clickhouse" or extra == "all"
Requires-Dist: colorama (>=0.4.6,<0.5.0)
Requires-Dist: duckdb (>=0.9.0,<0.10.0) ; extra == "csv" or extra == "all"
Requires-Dist: flask (>=3.0.3,<4.0.0)
Requires-Dist: mysql-connector-python (>=8.0.0,<9.0.0) ; extra == "mysql" or extra == "all"
Requires-Dist: openai (>=1.35.15,<2.0.0)
Requires-Dist: pdfkit (>=1.0.0,<2.0.0) ; extra == "pdf" or extra == "all"
Requires-Dist: psycopg2-binary (>=2.9.0,<3.0.0) ; extra == "postgres" or extra == "all"
Requires-Dist: pyaml (>=24.7.0,<25.0.0)
Requires-Dist: pyodbc (>=4.0.0,<5.0.0) ; extra == "mssql" or extra == "all"
Requires-Dist: pyyaml (>=6.0,<7.0)
Requires-Dist: requests (>=2.32.3,<3.0.0)
Requires-Dist: sqlparse (>=0.5.1,<0.6.0)
Requires-Dist: tabulate (>=0.9.0,<0.10.0)
